[{"id":1,"first_name":"Zelig","last_name":"Evens","email":"zevens0@com.com","date_of_birth":"1988-04-12T07:17:08Z","age":58,"country":"Sweden","phone":"8172226154"},
{"id":2,"first_name":"Pierre","last_name":"Barrington","email":"pbarrington1@ucoz.com","date_of_birth":"2011-07-13T23:05:37Z","age":39,"country":"Japan","phone":"8651176567"},
{"id":3,"first_name":"Torr","last_name":"Oertzen","email":"toertzen2@lulu.com","date_of_birth":"2016-08-28T12:25:04Z","age":43,"country":"China","phone":"1627100266"},
{"id":4,"first_name":"Lucille","last_name":"Elfes","email":"lelfes3@shutterfly.com","date_of_birth":"1974-05-22T18:46:38Z","age":28,"country":"Indonesia","phone":"2493449496"},
{"id":5,"first_name":"Andi","last_name":"Druhan","email":"adruhan4@prweb.com","date_of_birth":"1985-10-15T16:11:35Z","age":61,"country":"Cuba","phone":"7106926118"},
{"id":6,"first_name":"Holly","last_name":"Band","email":"hband5@edublogs.org","date_of_birth":"2007-04-04T10:06:10Z","age":36,"country":"China","phone":"7607347699"},
{"id":7,"first_name":"Deborah","last_name":"Clayal","email":"dclayal6@topsy.com","date_of_birth":"2020-05-30T17:08:02Z","age":30,"country":"Thailand","phone":"4325983718"},
{"id":8,"first_name":"Anatola","last_name":"Sapsed","email":"asapsed7@yelp.com","date_of_birth":"2019-12-31T18:26:56Z","age":52,"country":"United States","phone":"2564284694"},
{"id":9,"first_name":"Darleen","last_name":"Meese","email":"dmeese8@gravatar.com","date_of_birth":"1984-06-11T06:32:26Z","age":37,"country":"Russia","phone":"4468221013"},
{"id":10,"first_name":"Pen","last_name":"Raddan","email":"praddan9@washingtonpost.com","date_of_birth":"1971-12-06T12:36:58Z","age":20,"country":"Russia","phone":"3853065819"},
{"id":11,"first_name":"Yorgo","last_name":"Di Domenico","email":"ydidomenicoa@nbcnews.com","date_of_birth":"2014-11-23T20:35:50Z","age":51,"country":"Russia","phone":"3274972455"},
{"id":12,"first_name":"Donella","last_name":"Scading","email":"dscadingb@arstechnica.com","date_of_birth":"1981-06-22T16:00:01Z","age":35,"country":"Peru","phone":"5085157588"},
{"id":13,"first_name":"Orlan","last_name":"Piggott","email":"opiggottc@ftc.gov","date_of_birth":"1973-10-23T20:09:22Z","age":19,"country":"China","phone":"4755155602"},
{"id":14,"first_name":"Darill","last_name":"Iacovuzzi","email":"diacovuzzid@usnews.com","date_of_birth":"2000-10-27T13:10:59Z","age":46,"country":"Brazil","phone":"6328208288"},
{"id":15,"first_name":"Zaccaria","last_name":"Cady","email":"zcadye@netscape.com","date_of_birth":"1979-01-15T10:24:13Z","age":19,"country":"China","phone":"7646033085"},
{"id":16,"first_name":"Arly","last_name":"Tibalt","email":"atibaltf@columbia.edu","date_of_birth":"1990-02-19T14:41:54Z","age":53,"country":"Brazil","phone":"5415594790"},
{"id":17,"first_name":"Lanie","last_name":"Cookson","email":"lcooksong@newsvine.com","date_of_birth":"2021-12-24T01:51:34Z","age":34,"country":"Brazil","phone":"6046914361"},
{"id":18,"first_name":"Kevan","last_name":"Kira","email":"kkirah@spiegel.de","date_of_birth":"2001-05-07T07:03:40Z","age":23,"country":"Ukraine","phone":"5991602928"},
{"id":19,"first_name":"Renato","last_name":"Daldan","email":"rdaldani@alibaba.com","date_of_birth":"1991-12-05T16:09:51Z","age":19,"country":"Iraq","phone":"9802896457"},
{"id":20,"first_name":"Lyndel","last_name":"Aykroyd","email":"laykroydj@cornell.edu","date_of_birth":"1985-03-18T18:40:59Z","age":46,"country":"Poland","phone":"5777617662"},
{"id":21,"first_name":"Sargent","last_name":"Schroder","email":"sschroderk@msn.com","date_of_birth":"1997-06-25T01:08:24Z","age":47,"country":"United States","phone":"8508043618"},
{"id":22,"first_name":"Albrecht","last_name":"Brotherick","email":"abrotherickl@t.co","date_of_birth":"2013-11-16T07:58:28Z","age":23,"country":"China","phone":"8714691930"},
{"id":23,"first_name":"Leora","last_name":"Camidge","email":"lcamidgem@sogou.com","date_of_birth":"2015-03-25T19:33:44Z","age":30,"country":"France","phone":"2963952142"},
{"id":24,"first_name":"Rodina","last_name":"Downes","email":"rdownesn@wiley.com","date_of_birth":"1996-12-23T05:05:55Z","age":42,"country":"Colombia","phone":"7386636001"},
{"id":25,"first_name":"Michelina","last_name":"Mulqueen","email":"mmulqueeno@netvibes.com","date_of_birth":"1999-10-31T08:31:05Z","age":37,"country":"Canada","phone":"4361219866"},
{"id":26,"first_name":"Taryn","last_name":"Petrovykh","email":"tpetrovykhp@phoca.cz","date_of_birth":"2003-06-06T16:30:13Z","age":49,"country":"Philippines","phone":"6636336690"},
{"id":27,"first_name":"Matias","last_name":"Cheales","email":"mchealesq@miitbeian.gov.cn","date_of_birth":"1976-01-24T04:30:35Z","age":54,"country":"Germany","phone":"7834687913"},
{"id":28,"first_name":"Alecia","last_name":"Haley","email":"ahaleyr@livejournal.com","date_of_birth":"1993-03-16T15:19:44Z","age":32,"country":"China","phone":"6545539227"},
{"id":29,"first_name":"Hanan","last_name":"Daout","email":"hdaouts@census.gov","date_of_birth":"2012-12-22T18:38:48Z","age":34,"country":"China","phone":"7986516780"},
{"id":30,"first_name":"Guinevere","last_name":"Dorsey","email":"gdorseyt@ask.com","date_of_birth":"2012-05-23T05:47:32Z","age":55,"country":"China","phone":"4361675159"},
{"id":31,"first_name":"Cherin","last_name":"Stoggles","email":"cstogglesu@fotki.com","date_of_birth":"2007-07-30T10:10:43Z","age":32,"country":"Ghana","phone":"5637484133"},
{"id":32,"first_name":"Lorenza","last_name":"Burnand","email":"lburnandv@pen.io","date_of_birth":"1999-05-05T09:48:38Z","age":22,"country":"China","phone":"9644793448"},
{"id":33,"first_name":"Melosa","last_name":"Epton","email":"meptonw@imageshack.us","date_of_birth":"2006-10-13T19:00:35Z","age":44,"country":"Indonesia","phone":"7379488729"},
{"id":34,"first_name":"Suzette","last_name":"Heaney","email":"sheaneyx@macromedia.com","date_of_birth":"2023-01-06T00:54:32Z","age":36,"country":"Poland","phone":"3755604399"},
{"id":35,"first_name":"Benn","last_name":"Davall","email":"bdavally@economist.com","date_of_birth":"2006-05-25T22:08:08Z","age":43,"country":"Indonesia","phone":"8124965214"},
{"id":36,"first_name":"Dominick","last_name":"Ferreras","email":"dferrerasz@freewebs.com","date_of_birth":"1989-02-21T21:40:47Z","age":40,"country":"North Korea","phone":"3485400982"},
{"id":37,"first_name":"Adorne","last_name":"Ruzek","email":"aruzek10@networksolutions.com","date_of_birth":"2019-12-19T01:11:59Z","age":50,"country":"Sweden","phone":"6562002298"},
{"id":38,"first_name":"Andreana","last_name":"Wasbey","email":"awasbey11@independent.co.uk","date_of_birth":"2021-08-29T05:13:49Z","age":26,"country":"Russia","phone":"5607871505"},
{"id":39,"first_name":"Camey","last_name":"Viollet","email":"cviollet12@ning.com","date_of_birth":"2003-02-27T21:11:20Z","age":59,"country":"Portugal","phone":"1325538831"},
{"id":40,"first_name":"Kenny","last_name":"Glowinski","email":"kglowinski13@photobucket.com","date_of_birth":"2015-02-01T10:06:30Z","age":43,"country":"Canada","phone":"6204331078"},
{"id":41,"first_name":"Kermie","last_name":"Lurner","email":"klurner14@printfriendly.com","date_of_birth":"1973-10-21T19:52:42Z","age":52,"country":"Portugal","phone":"7179453751"},
{"id":42,"first_name":"Merna","last_name":"Gippes","email":"mgippes15@is.gd","date_of_birth":"2003-09-19T17:48:35Z","age":44,"country":"Indonesia","phone":"8436168109"},
{"id":43,"first_name":"Liane","last_name":"MacElroy","email":"lmacelroy16@lulu.com","date_of_birth":"2021-09-02T03:43:55Z","age":21,"country":"Mongolia","phone":"5827894331"},
{"id":44,"first_name":"Sunny","last_name":"Morcomb","email":"smorcomb17@tamu.edu","date_of_birth":"1980-08-14T09:24:02Z","age":19,"country":"Czech Republic","phone":"4446911289"},
{"id":45,"first_name":"Isac","last_name":"Haggish","email":"ihaggish18@prweb.com","date_of_birth":"1987-12-31T08:19:32Z","age":43,"country":"Finland","phone":"9118315337"},
{"id":46,"first_name":"Angeline","last_name":"Simoni","email":"asimoni19@timesonline.co.uk","date_of_birth":"2009-11-19T05:49:18Z","age":33,"country":"Poland","phone":"5557859780"},
{"id":47,"first_name":"Michale","last_name":"Biernacki","email":"mbiernacki1a@mac.com","date_of_birth":"1977-02-24T11:30:57Z","age":52,"country":"Nigeria","phone":"8289364799"},
{"id":48,"first_name":"Adlai","last_name":"Jurisic","email":"ajurisic1b@ow.ly","date_of_birth":"1971-12-14T02:54:09Z","age":34,"country":"Canada","phone":"8574522168"},
{"id":49,"first_name":"Bobinette","last_name":"Midner","email":"bmidner1c@google.ca","date_of_birth":"2012-01-22T04:42:00Z","age":63,"country":"Ukraine","phone":"1929713107"},
{"id":50,"first_name":"Edythe","last_name":"Nobes","email":"enobes1d@wufoo.com","date_of_birth":"2003-10-08T15:51:57Z","age":49,"country":"Indonesia","phone":"8889387393"},
{"id":51,"first_name":"Kenon","last_name":"Sparey","email":"ksparey1e@sfgate.com","date_of_birth":"1977-08-16T01:06:11Z","age":40,"country":"Canada","phone":"7525935293"},
{"id":52,"first_name":"Marna","last_name":"Hatterslay","email":"mhatterslay1f@salon.com","date_of_birth":"1981-03-18T22:15:06Z","age":44,"country":"Sierra Leone","phone":"1419995569"},
{"id":53,"first_name":"Stevena","last_name":"Emmison","email":"semmison1g@opera.com","date_of_birth":"2001-09-04T01:11:51Z","age":53,"country":"Bahamas","phone":"6723287545"},
{"id":54,"first_name":"Dietrich","last_name":"Rossbrooke","email":"drossbrooke1h@howstuffworks.com","date_of_birth":"1976-02-04T12:39:24Z","age":62,"country":"China","phone":"5823776766"},
{"id":55,"first_name":"Nicky","last_name":"Gosenell","email":"ngosenell1i@thetimes.co.uk","date_of_birth":"1999-08-10T00:59:25Z","age":21,"country":"Brazil","phone":"1108064999"},
{"id":56,"first_name":"Paolina","last_name":"Lill","email":"plill1j@psu.edu","date_of_birth":"1976-04-14T03:37:27Z","age":49,"country":"Peru","phone":"8982176424"},
{"id":57,"first_name":"Elane","last_name":"Ferrar","email":"eferrar1k@nsw.gov.au","date_of_birth":"1972-02-21T16:44:30Z","age":48,"country":"Martinique","phone":"7083055208"},
{"id":58,"first_name":"Jenna","last_name":"Howse","email":"jhowse1l@jalbum.net","date_of_birth":"1992-02-20T00:01:52Z","age":40,"country":"United States","phone":"9703906283"},
{"id":59,"first_name":"Whitney","last_name":"O'Carney","email":"wocarney1m@skype.com","date_of_birth":"1978-11-11T14:03:36Z","age":39,"country":"Brazil","phone":"7809943130"},
{"id":60,"first_name":"Vin","last_name":"Fearby","email":"vfearby1n@usda.gov","date_of_birth":"1996-03-24T22:45:47Z","age":37,"country":"China","phone":"1389641968"},
{"id":61,"first_name":"Doloritas","last_name":"MacAlester","email":"dmacalester1o@mashable.com","date_of_birth":"2016-04-24T19:18:57Z","age":19,"country":"Poland","phone":"8349922730"},
{"id":62,"first_name":"Ceciley","last_name":"Konneke","email":"ckonneke1p@go.com","date_of_birth":"2019-11-29T13:18:47Z","age":45,"country":"Russia","phone":"5475766004"},
{"id":63,"first_name":"Teddi","last_name":"Arundel","email":"tarundel1q@jiathis.com","date_of_birth":"1989-05-24T13:17:28Z","age":46,"country":"Mexico","phone":"3034104787"},
{"id":64,"first_name":"Moe","last_name":"Style","email":"mstyle1r@soup.io","date_of_birth":"2006-12-17T01:51:07Z","age":59,"country":"Sweden","phone":"6258612086"},
{"id":65,"first_name":"Jacqueline","last_name":"Mardall","email":"jmardall1s@livejournal.com","date_of_birth":"2022-01-10T09:16:50Z","age":33,"country":"China","phone":"3259562275"},
{"id":66,"first_name":"Perry","last_name":"Simmens","email":"psimmens1t@tripod.com","date_of_birth":"1979-01-03T14:53:15Z","age":34,"country":"Japan","phone":"9136381964"},
{"id":67,"first_name":"Godart","last_name":"Handman","email":"ghandman1u@house.gov","date_of_birth":"2017-03-24T12:09:28Z","age":57,"country":"Colombia","phone":"9773161878"},
{"id":68,"first_name":"Renie","last_name":"Camelia","email":"rcamelia1v@google.nl","date_of_birth":"2002-10-29T13:49:33Z","age":19,"country":"Ukraine","phone":"8865945659"},
{"id":69,"first_name":"Katrinka","last_name":"Triggol","email":"ktriggol1w@yale.edu","date_of_birth":"1973-02-18T01:01:14Z","age":37,"country":"China","phone":"3349772701"},
{"id":70,"first_name":"Dreddy","last_name":"Aartsen","email":"daartsen1x@opensource.org","date_of_birth":"1974-07-10T03:04:30Z","age":51,"country":"Philippines","phone":"7094215890"},
{"id":71,"first_name":"Dale","last_name":"Kaes","email":"dkaes1y@posterous.com","date_of_birth":"2019-05-12T05:12:49Z","age":46,"country":"Sweden","phone":"5742845553"},
{"id":72,"first_name":"Julie","last_name":"Edbrooke","email":"jedbrooke1z@sakura.ne.jp","date_of_birth":"1981-04-15T05:51:36Z","age":32,"country":"American Samoa","phone":"1492688775"},
{"id":73,"first_name":"Martino","last_name":"Snasel","email":"msnasel20@ucsd.edu","date_of_birth":"1987-07-06T01:10:20Z","age":29,"country":"Indonesia","phone":"2658019182"},
{"id":74,"first_name":"Jamey","last_name":"Lawee","email":"jlawee21@dyndns.org","date_of_birth":"2022-08-24T02:15:39Z","age":51,"country":"United States","phone":"7025259836"},
{"id":75,"first_name":"Lorin","last_name":"Steen","email":"lsteen22@amazon.com","date_of_birth":"1993-08-21T19:58:44Z","age":48,"country":"Russia","phone":"9297726447"},
{"id":76,"first_name":"Jon","last_name":"Rearie","email":"jrearie23@networkadvertising.org","date_of_birth":"2002-07-15T02:23:44Z","age":63,"country":"Brazil","phone":"1112267580"},
{"id":77,"first_name":"Germain","last_name":"Tradewell","email":"gtradewell24@house.gov","date_of_birth":"2016-02-02T01:44:39Z","age":62,"country":"China","phone":"7055660025"},
{"id":78,"first_name":"Jessie","last_name":"Henzley","email":"jhenzley25@feedburner.com","date_of_birth":"1990-07-22T21:51:20Z","age":43,"country":"Sweden","phone":"7799659422"},
{"id":79,"first_name":"Griffin","last_name":"Lantuffe","email":"glantuffe26@moonfruit.com","date_of_birth":"2004-03-29T04:35:25Z","age":43,"country":"Philippines","phone":"6288681747"},
{"id":80,"first_name":"Eva","last_name":"Swancock","email":"eswancock27@nih.gov","date_of_birth":"2010-01-30T13:33:48Z","age":23,"country":"China","phone":"1663185974"},
{"id":81,"first_name":"Codie","last_name":"Brisseau","email":"cbrisseau28@bbc.co.uk","date_of_birth":"2019-09-19T20:54:21Z","age":47,"country":"Norway","phone":"6388505700"},
{"id":82,"first_name":"Vanessa","last_name":"Fancourt","email":"vfancourt29@time.com","date_of_birth":"2003-06-29T02:22:54Z","age":40,"country":"Netherlands","phone":"2582447168"},
{"id":83,"first_name":"Barbee","last_name":"Kimblin","email":"bkimblin2a@wp.com","date_of_birth":"1983-09-14T21:02:04Z","age":54,"country":"Serbia","phone":"6802296419"},
{"id":84,"first_name":"Koral","last_name":"Maidment","email":"kmaidment2b@dailymail.co.uk","date_of_birth":"2009-05-19T07:24:55Z","age":56,"country":"Sweden","phone":"9664452783"},
{"id":85,"first_name":"Petronia","last_name":"Lowbridge","email":"plowbridge2c@oracle.com","date_of_birth":"2000-10-21T15:02:57Z","age":56,"country":"China","phone":"7694357046"},
{"id":86,"first_name":"Alane","last_name":"Dehn","email":"adehn2d@dailymotion.com","date_of_birth":"1987-11-24T08:55:23Z","age":44,"country":"Portugal","phone":"1049558659"},
{"id":87,"first_name":"Libbey","last_name":"Jerram","email":"ljerram2e@acquirethisname.com","date_of_birth":"1998-03-25T05:10:12Z","age":18,"country":"United States","phone":"8163237307"},
{"id":88,"first_name":"Freddi","last_name":"Cawood","email":"fcawood2f@joomla.org","date_of_birth":"2022-11-11T17:32:05Z","age":43,"country":"Croatia","phone":"3735161547"},
{"id":89,"first_name":"Elizabet","last_name":"Sandwich","email":"esandwich2g@ed.gov","date_of_birth":"2009-08-05T12:58:56Z","age":62,"country":"Sweden","phone":"3612995650"},
{"id":90,"first_name":"Cristian","last_name":"Gisbourn","email":"cgisbourn2h@mapy.cz","date_of_birth":"1989-08-07T04:52:32Z","age":30,"country":"Indonesia","phone":"5058314574"},
{"id":91,"first_name":"Ninon","last_name":"Mordie","email":"nmordie2i@mashable.com","date_of_birth":"1993-02-18T06:49:04Z","age":60,"country":"Indonesia","phone":"6494044438"},
{"id":92,"first_name":"Dell","last_name":"Garrie","email":"dgarrie2j@issuu.com","date_of_birth":"2012-07-29T18:56:18Z","age":47,"country":"Madagascar","phone":"2055501123"},
{"id":93,"first_name":"Felicle","last_name":"Taffley","email":"ftaffley2k@omniture.com","date_of_birth":"1988-06-02T02:12:50Z","age":51,"country":"Philippines","phone":"7088864037"},
{"id":94,"first_name":"Dale","last_name":"Bewfield","email":"dbewfield2l@over-blog.com","date_of_birth":"1984-03-05T13:33:58Z","age":37,"country":"Central African Republic","phone":"7736814566"},
{"id":95,"first_name":"Nada","last_name":"Downham","email":"ndownham2m@ehow.com","date_of_birth":"1994-08-31T14:25:26Z","age":28,"country":"Colombia","phone":"6052140030"},
{"id":96,"first_name":"Ernest","last_name":"Parman","email":"eparman2n@seattletimes.com","date_of_birth":"1986-12-16T05:50:04Z","age":55,"country":"Slovenia","phone":"9906369006"},
{"id":97,"first_name":"Nicolette","last_name":"Gerrell","email":"ngerrell2o@theatlantic.com","date_of_birth":"2003-11-10T04:08:24Z","age":59,"country":"Pakistan","phone":"1054763413"},
{"id":98,"first_name":"Estel","last_name":"Jachimak","email":"ejachimak2p@sakura.ne.jp","date_of_birth":"1983-07-29T02:14:51Z","age":61,"country":"Kyrgyzstan","phone":"4854629418"},
{"id":99,"first_name":"Gabie","last_name":"Ewin","email":"gewin2q@fc2.com","date_of_birth":"2012-02-17T19:37:26Z","age":44,"country":"Serbia","phone":"9316016237"},
{"id":100,"first_name":"Cordie","last_name":"Waiton","email":"cwaiton2r@posterous.com","date_of_birth":"1992-10-21T20:45:55Z","age":53,"country":"Sweden","phone":"5489367915"},
{"id":101,"first_name":"Merv","last_name":"Vuitte","email":"mvuitte2s@telegraph.co.uk","date_of_birth":"2009-06-24T08:39:53Z","age":32,"country":"Cuba","phone":"2884954586"},
{"id":102,"first_name":"Gilli","last_name":"Harvett","email":"gharvett2t@tamu.edu","date_of_birth":"2018-08-12T20:54:07Z","age":60,"country":"China","phone":"3871137071"},
{"id":103,"first_name":"Barnett","last_name":"Corn","email":"bcorn2u@rakuten.co.jp","date_of_birth":"1983-07-29T03:27:45Z","age":21,"country":"Poland","phone":"8389605555"},
{"id":104,"first_name":"Rikki","last_name":"Barmby","email":"rbarmby2v@ycombinator.com","date_of_birth":"1980-07-12T03:53:34Z","age":40,"country":"Brazil","phone":"3911443589"},
{"id":105,"first_name":"Candice","last_name":"Samet","email":"csamet2w@cocolog-nifty.com","date_of_birth":"1991-12-01T19:38:38Z","age":48,"country":"Brazil","phone":"7588104803"},
{"id":106,"first_name":"Kalle","last_name":"Beers","email":"kbeers2x@4shared.com","date_of_birth":"1993-05-16T11:21:32Z","age":27,"country":"China","phone":"7391828198"},
{"id":107,"first_name":"Thelma","last_name":"New","email":"tnew2y@dedecms.com","date_of_birth":"1982-02-28T02:29:22Z","age":37,"country":"China","phone":"4677845967"},
{"id":108,"first_name":"Cris","last_name":"Enrique","email":"cenrique2z@noaa.gov","date_of_birth":"2017-09-15T11:13:50Z","age":47,"country":"Somalia","phone":"7127904890"},
{"id":109,"first_name":"Pancho","last_name":"Tolmie","email":"ptolmie30@vkontakte.ru","date_of_birth":"1972-01-04T07:08:36Z","age":19,"country":"Portugal","phone":"5813784701"},
{"id":110,"first_name":"Candis","last_name":"Staveley","email":"cstaveley31@mail.ru","date_of_birth":"1976-02-07T08:20:09Z","age":26,"country":"Tanzania","phone":"5047263983"},
{"id":111,"first_name":"Paige","last_name":"Belitz","email":"pbelitz32@usnews.com","date_of_birth":"1991-04-04T06:58:12Z","age":42,"country":"Indonesia","phone":"6285743096"},
{"id":112,"first_name":"Hilary","last_name":"Hebner","email":"hhebner33@so-net.ne.jp","date_of_birth":"1971-03-25T19:08:51Z","age":32,"country":"South Africa","phone":"2597944383"},
{"id":113,"first_name":"Denni","last_name":"Aron","email":"daron34@mysql.com","date_of_birth":"1985-12-29T07:41:39Z","age":33,"country":"Portugal","phone":"7518521805"},
{"id":114,"first_name":"Peter","last_name":"Grzeskowski","email":"pgrzeskowski35@studiopress.com","date_of_birth":"1995-12-14T04:23:31Z","age":59,"country":"Russia","phone":"7014297815"},
{"id":115,"first_name":"Blondelle","last_name":"Portis","email":"bportis36@shop-pro.jp","date_of_birth":"1998-12-19T23:20:07Z","age":42,"country":"Madagascar","phone":"2568835160"},
{"id":116,"first_name":"Jaine","last_name":"Hadigate","email":"jhadigate37@addtoany.com","date_of_birth":"2003-06-09T17:54:01Z","age":38,"country":"Indonesia","phone":"9529376559"},
{"id":117,"first_name":"Caren","last_name":"Van der Velden","email":"cvandervelden38@deviantart.com","date_of_birth":"1990-11-07T14:04:43Z","age":61,"country":"Panama","phone":"2728936324"},
{"id":118,"first_name":"Malissia","last_name":"Ecob","email":"mecob39@columbia.edu","date_of_birth":"1974-10-05T04:36:28Z","age":40,"country":"Indonesia","phone":"8071432559"},
{"id":119,"first_name":"Adriana","last_name":"Jancey","email":"ajancey3a@soundcloud.com","date_of_birth":"1992-09-22T10:53:12Z","age":57,"country":"Sweden","phone":"1511420931"},
{"id":120,"first_name":"Reinald","last_name":"Lawes","email":"rlawes3b@ask.com","date_of_birth":"2021-04-15T22:09:23Z","age":56,"country":"Indonesia","phone":"9607811320"},
{"id":121,"first_name":"Edin","last_name":"Welsh","email":"ewelsh3c@pbs.org","date_of_birth":"2013-07-28T18:28:02Z","age":46,"country":"Russia","phone":"6623229345"},
{"id":122,"first_name":"Deva","last_name":"Staig","email":"dstaig3d@tiny.cc","date_of_birth":"1992-09-21T23:48:13Z","age":20,"country":"Poland","phone":"8743636142"},
{"id":123,"first_name":"Merwyn","last_name":"Sumshon","email":"msumshon3e@cargocollective.com","date_of_birth":"1974-08-29T16:20:50Z","age":52,"country":"Brazil","phone":"4169284317"},
{"id":124,"first_name":"Dulcinea","last_name":"Caras","email":"dcaras3f@ask.com","date_of_birth":"2004-02-12T00:07:10Z","age":38,"country":"China","phone":"1282053997"},
{"id":125,"first_name":"Germain","last_name":"Pirrey","email":"gpirrey3g@economist.com","date_of_birth":"1976-08-11T13:52:16Z","age":52,"country":"Indonesia","phone":"2066578825"},
{"id":126,"first_name":"Emmeline","last_name":"Remon","email":"eremon3h@ox.ac.uk","date_of_birth":"2016-02-04T16:50:10Z","age":42,"country":"Poland","phone":"6727216720"},
{"id":127,"first_name":"Almeria","last_name":"Quartly","email":"aquartly3i@lycos.com","date_of_birth":"1971-05-11T21:09:37Z","age":33,"country":"China","phone":"6174786111"},
{"id":128,"first_name":"Cyndia","last_name":"Christon","email":"cchriston3j@dell.com","date_of_birth":"2012-12-11T04:34:54Z","age":52,"country":"Indonesia","phone":"3349818386"},
{"id":129,"first_name":"Keeley","last_name":"Gladhill","email":"kgladhill3k@seesaa.net","date_of_birth":"1995-12-02T09:04:56Z","age":25,"country":"Tajikistan","phone":"2797837875"},
{"id":130,"first_name":"Ned","last_name":"Pinnion","email":"npinnion3l@samsung.com","date_of_birth":"2000-03-01T14:54:42Z","age":51,"country":"Belarus","phone":"9095921354"},
{"id":131,"first_name":"Torey","last_name":"Fraczkiewicz","email":"tfraczkiewicz3m@indiegogo.com","date_of_birth":"2014-01-28T11:10:05Z","age":42,"country":"China","phone":"3269640608"},
{"id":132,"first_name":"Donny","last_name":"Ratnege","email":"dratnege3n@ow.ly","date_of_birth":"2021-01-09T05:36:01Z","age":18,"country":"China","phone":"2265411510"},
{"id":133,"first_name":"Jenn","last_name":"Peasnone","email":"jpeasnone3o@drupal.org","date_of_birth":"2002-03-19T06:52:23Z","age":63,"country":"Brazil","phone":"3264488580"},
{"id":134,"first_name":"Brent","last_name":"Skunes","email":"bskunes3p@ucoz.ru","date_of_birth":"2015-11-29T14:54:53Z","age":25,"country":"Ecuador","phone":"1922535801"},
{"id":135,"first_name":"Merrick","last_name":"Gillcrist","email":"mgillcrist3q@biblegateway.com","date_of_birth":"1995-12-26T22:20:06Z","age":25,"country":"Vietnam","phone":"6396833662"},
{"id":136,"first_name":"Zorine","last_name":"Fairney","email":"zfairney3r@google.fr","date_of_birth":"2012-03-27T06:05:45Z","age":55,"country":"Japan","phone":"3362469865"},
{"id":137,"first_name":"Bellanca","last_name":"Antoniewski","email":"bantoniewski3s@bravesites.com","date_of_birth":"1983-03-12T12:50:03Z","age":24,"country":"Russia","phone":"9862224076"},
{"id":138,"first_name":"Briney","last_name":"Drogan","email":"bdrogan3t@de.vu","date_of_birth":"2009-03-24T13:36:01Z","age":38,"country":"China","phone":"9428572113"},
{"id":139,"first_name":"Waneta","last_name":"Alldridge","email":"walldridge3u@amazon.com","date_of_birth":"2009-08-31T18:20:23Z","age":51,"country":"Thailand","phone":"2291311849"},
{"id":140,"first_name":"Meredeth","last_name":"Hiner","email":"mhiner3v@seattletimes.com","date_of_birth":"1998-04-10T17:09:52Z","age":37,"country":"China","phone":"3892070166"},
{"id":141,"first_name":"Malory","last_name":"Giles","email":"mgiles3w@purevolume.com","date_of_birth":"1989-09-02T12:00:59Z","age":30,"country":"Syria","phone":"6029773261"},
{"id":142,"first_name":"Glenna","last_name":"Handscomb","email":"ghandscomb3x@latimes.com","date_of_birth":"1989-01-31T03:47:44Z","age":59,"country":"Indonesia","phone":"1304037950"},
{"id":143,"first_name":"Wandie","last_name":"Celes","email":"wceles3y@goodreads.com","date_of_birth":"2005-02-23T00:48:25Z","age":46,"country":"Japan","phone":"3703819893"},
{"id":144,"first_name":"Aileen","last_name":"Puve","email":"apuve3z@cbsnews.com","date_of_birth":"1985-02-07T09:40:59Z","age":57,"country":"Mongolia","phone":"9944218527"},
{"id":145,"first_name":"Celka","last_name":"Aldrick","email":"caldrick40@cmu.edu","date_of_birth":"1993-07-08T05:27:49Z","age":46,"country":"China","phone":"7117099951"},
{"id":146,"first_name":"Alysia","last_name":"Boffin","email":"aboffin41@bloglines.com","date_of_birth":"1993-08-10T21:46:09Z","age":46,"country":"United States","phone":"2022403897"},
{"id":147,"first_name":"Courtnay","last_name":"Covet","email":"ccovet42@businessweek.com","date_of_birth":"1985-01-09T10:28:24Z","age":47,"country":"China","phone":"7691539147"},
{"id":148,"first_name":"Jo-ann","last_name":"Crim","email":"jcrim43@miitbeian.gov.cn","date_of_birth":"2020-08-26T21:44:40Z","age":45,"country":"China","phone":"4993779961"},
{"id":149,"first_name":"Silvie","last_name":"Gammade","email":"sgammade44@oaic.gov.au","date_of_birth":"1988-05-09T07:10:46Z","age":25,"country":"Portugal","phone":"3821899888"},
{"id":150,"first_name":"Orsa","last_name":"Cullingworth","email":"ocullingworth45@youku.com","date_of_birth":"2005-03-30T23:08:00Z","age":61,"country":"Indonesia","phone":"3196537715"},
{"id":151,"first_name":"Chan","last_name":"Donke","email":"cdonke46@plala.or.jp","date_of_birth":"1988-06-22T08:33:29Z","age":42,"country":"Japan","phone":"7472968992"},
{"id":152,"first_name":"Henriette","last_name":"Eannetta","email":"heannetta47@blogtalkradio.com","date_of_birth":"2021-06-05T16:10:10Z","age":48,"country":"Japan","phone":"3145486050"},
{"id":153,"first_name":"Vinita","last_name":"Gilardengo","email":"vgilardengo48@unc.edu","date_of_birth":"2010-12-21T19:01:31Z","age":43,"country":"Czech Republic","phone":"9605388881"},
{"id":154,"first_name":"Svend","last_name":"Hyslop","email":"shyslop49@hexun.com","date_of_birth":"1997-06-17T12:46:29Z","age":44,"country":"Aland Islands","phone":"1586593119"},
{"id":155,"first_name":"Mariquilla","last_name":"Eyers","email":"meyers4a@arizona.edu","date_of_birth":"1982-07-04T07:40:58Z","age":36,"country":"Russia","phone":"8477592545"},
{"id":156,"first_name":"Pat","last_name":"Aguirrezabala","email":"paguirrezabala4b@wired.com","date_of_birth":"2013-06-28T09:04:15Z","age":37,"country":"Croatia","phone":"3745833837"},
{"id":157,"first_name":"Freda","last_name":"Grason","email":"fgrason4c@free.fr","date_of_birth":"1983-12-14T19:44:21Z","age":40,"country":"Somalia","phone":"8224094898"},
{"id":158,"first_name":"Lou","last_name":"Langshaw","email":"llangshaw4d@cisco.com","date_of_birth":"1991-01-25T07:50:35Z","age":44,"country":"Czech Republic","phone":"8162237286"},
{"id":159,"first_name":"Wade","last_name":"Labell","email":"wlabell4e@aol.com","date_of_birth":"1975-09-06T03:02:57Z","age":18,"country":"Indonesia","phone":"2054974686"},
{"id":160,"first_name":"Becki","last_name":"Fidler","email":"bfidler4f@mapy.cz","date_of_birth":"2010-08-11T07:40:31Z","age":56,"country":"Russia","phone":"9632581579"},
{"id":161,"first_name":"Chelsey","last_name":"Miko","email":"cmiko4g@wufoo.com","date_of_birth":"2006-05-02T07:52:04Z","age":18,"country":"Colombia","phone":"9799084484"},
{"id":162,"first_name":"Hyman","last_name":"Atcheson","email":"hatcheson4h@buzzfeed.com","date_of_birth":"1991-01-17T03:35:01Z","age":53,"country":"United States","phone":"7727969382"},
{"id":163,"first_name":"Eustace","last_name":"Melody","email":"emelody4i@google.ca","date_of_birth":"2022-04-29T20:51:24Z","age":18,"country":"China","phone":"7471937934"},
{"id":164,"first_name":"Hastie","last_name":"Hadny","email":"hhadny4j@youtu.be","date_of_birth":"2009-11-05T08:38:49Z","age":36,"country":"Ecuador","phone":"5858612204"},
{"id":165,"first_name":"Aubree","last_name":"Gritten","email":"agritten4k@youtu.be","date_of_birth":"2013-04-23T05:19:27Z","age":62,"country":"United States","phone":"7572897601"},
{"id":166,"first_name":"Candice","last_name":"Folley","email":"cfolley4l@gmpg.org","date_of_birth":"1984-06-05T00:29:03Z","age":58,"country":"Thailand","phone":"8321842104"},
{"id":167,"first_name":"Norton","last_name":"Meldon","email":"nmeldon4m@nps.gov","date_of_birth":"2003-02-03T19:06:35Z","age":25,"country":"Indonesia","phone":"5851433976"},
{"id":168,"first_name":"Corilla","last_name":"Flewett","email":"cflewett4n@sourceforge.net","date_of_birth":"2017-12-15T05:57:58Z","age":46,"country":"Indonesia","phone":"7967682657"},
{"id":169,"first_name":"Margi","last_name":"Duguid","email":"mduguid4o@china.com.cn","date_of_birth":"1982-06-05T19:27:32Z","age":58,"country":"Indonesia","phone":"2986750539"},
{"id":170,"first_name":"Bert","last_name":"Rao","email":"brao4p@rakuten.co.jp","date_of_birth":"1980-02-27T15:54:42Z","age":20,"country":"Russia","phone":"6554936619"},
{"id":171,"first_name":"Florentia","last_name":"Adamik","email":"fadamik4q@bigcartel.com","date_of_birth":"2020-03-27T00:47:26Z","age":58,"country":"China","phone":"8959818393"},
{"id":172,"first_name":"Byran","last_name":"Fidele","email":"bfidele4r@alexa.com","date_of_birth":"2008-07-03T12:27:47Z","age":62,"country":"China","phone":"4293750610"},
{"id":173,"first_name":"Roch","last_name":"Abbatucci","email":"rabbatucci4s@ucsd.edu","date_of_birth":"1970-04-23T20:30:58Z","age":27,"country":"Slovenia","phone":"6444338094"},
{"id":174,"first_name":"Liliane","last_name":"Hulke","email":"lhulke4t@nydailynews.com","date_of_birth":"2003-04-23T22:50:25Z","age":29,"country":"Guinea","phone":"9629774420"},
{"id":175,"first_name":"Ardelia","last_name":"Kennon","email":"akennon4u@domainmarket.com","date_of_birth":"2014-05-28T02:40:47Z","age":27,"country":"Indonesia","phone":"4785775811"},
{"id":176,"first_name":"Milli","last_name":"Itschakov","email":"mitschakov4v@purevolume.com","date_of_birth":"1998-05-19T07:16:54Z","age":25,"country":"Indonesia","phone":"5937667630"},
{"id":177,"first_name":"Avram","last_name":"Regi","email":"aregi4w@nymag.com","date_of_birth":"2015-08-12T15:25:31Z","age":27,"country":"Indonesia","phone":"2587648729"},
{"id":178,"first_name":"Fritz","last_name":"Thompkins","email":"fthompkins4x@stanford.edu","date_of_birth":"2006-07-01T11:14:50Z","age":63,"country":"Philippines","phone":"2884374786"},
{"id":179,"first_name":"Emalia","last_name":"Saben","email":"esaben4y@theatlantic.com","date_of_birth":"1972-03-22T02:09:44Z","age":21,"country":"Azerbaijan","phone":"5016926767"},
{"id":180,"first_name":"Alonso","last_name":"Souley","email":"asouley4z@fc2.com","date_of_birth":"2011-10-18T04:50:02Z","age":22,"country":"Russia","phone":"9663671863"},
{"id":181,"first_name":"Keelby","last_name":"Gellert","email":"kgellert50@fastcompany.com","date_of_birth":"2017-12-30T13:53:05Z","age":39,"country":"Brazil","phone":"8924511598"},
{"id":182,"first_name":"Lina","last_name":"Cryer","email":"lcryer51@netvibes.com","date_of_birth":"1996-11-26T00:16:52Z","age":38,"country":"Morocco","phone":"5683453457"},
{"id":183,"first_name":"Caryl","last_name":"Whyborn","email":"cwhyborn52@nifty.com","date_of_birth":"2003-01-12T14:16:41Z","age":21,"country":"Papua New Guinea","phone":"8854296376"},
{"id":184,"first_name":"Mitchael","last_name":"Cockayne","email":"mcockayne53@chicagotribune.com","date_of_birth":"2012-06-10T01:30:13Z","age":22,"country":"China","phone":"1264449513"},
{"id":185,"first_name":"Dion","last_name":"Jaycocks","email":"djaycocks54@intel.com","date_of_birth":"1993-12-16T12:22:00Z","age":25,"country":"Ukraine","phone":"1009760044"},
{"id":186,"first_name":"Fidelity","last_name":"Fellibrand","email":"ffellibrand55@booking.com","date_of_birth":"2014-09-17T20:34:04Z","age":46,"country":"Portugal","phone":"9423171391"},
{"id":187,"first_name":"Katherina","last_name":"Perrat","email":"kperrat56@smh.com.au","date_of_birth":"1985-05-14T17:14:35Z","age":20,"country":"Cuba","phone":"5796516249"},
{"id":188,"first_name":"Julius","last_name":"Chong","email":"jchong57@de.vu","date_of_birth":"1981-09-26T10:38:40Z","age":30,"country":"Thailand","phone":"7436698222"},
{"id":189,"first_name":"Jamaal","last_name":"Tatam","email":"jtatam58@wunderground.com","date_of_birth":"1981-11-19T06:42:30Z","age":51,"country":"China","phone":"5665131610"},
{"id":190,"first_name":"Udale","last_name":"Giral","email":"ugiral59@biglobe.ne.jp","date_of_birth":"2023-10-25T14:10:51Z","age":60,"country":"Greece","phone":"6323495625"},
{"id":191,"first_name":"Jecho","last_name":"Snaden","email":"jsnaden5a@studiopress.com","date_of_birth":"2018-09-22T16:55:44Z","age":24,"country":"Indonesia","phone":"1506325765"},
{"id":192,"first_name":"Mycah","last_name":"Upshall","email":"mupshall5b@phoca.cz","date_of_birth":"2009-05-29T17:51:56Z","age":36,"country":"Philippines","phone":"4925354729"},
{"id":193,"first_name":"Pam","last_name":"Mozzi","email":"pmozzi5c@booking.com","date_of_birth":"1984-12-12T02:49:43Z","age":43,"country":"Netherlands","phone":"2858945258"},
{"id":194,"first_name":"Nona","last_name":"Archibald","email":"narchibald5d@sciencedaily.com","date_of_birth":"2013-02-14T21:17:26Z","age":58,"country":"Philippines","phone":"8812125571"},
{"id":195,"first_name":"Geordie","last_name":"Sollam","email":"gsollam5e@answers.com","date_of_birth":"1994-01-28T02:07:27Z","age":60,"country":"China","phone":"6975560440"},
{"id":196,"first_name":"Theobald","last_name":"Goathrop","email":"tgoathrop5f@cdbaby.com","date_of_birth":"1976-07-31T21:37:39Z","age":46,"country":"Bangladesh","phone":"3563524984"},
{"id":197,"first_name":"Nina","last_name":"Danbrook","email":"ndanbrook5g@rambler.ru","date_of_birth":"1983-03-02T14:48:43Z","age":47,"country":"China","phone":"4355863328"},
{"id":198,"first_name":"Moira","last_name":"Silverthorne","email":"msilverthorne5h@usatoday.com","date_of_birth":"2019-12-20T21:12:36Z","age":32,"country":"Albania","phone":"8939794789"},
{"id":199,"first_name":"Kelwin","last_name":"Stutt","email":"kstutt5i@globo.com","date_of_birth":"1985-06-01T07:04:29Z","age":37,"country":"China","phone":"1325062892"},
{"id":200,"first_name":"Demetria","last_name":"Stallon","email":"dstallon5j@huffingtonpost.com","date_of_birth":"2006-06-07T23:25:47Z","age":40,"country":"China","phone":"8283409421"}]